scenario_gym/__init__.py
scenario_gym/action.py
scenario_gym/agent.py
scenario_gym/callback.py
scenario_gym/catalog_entry.py
scenario_gym/controller.py
scenario_gym/manager.py
scenario_gym/observation.py
scenario_gym/scenario_gym.py
scenario_gym/trajectory.py
scenario_gym/utils.py
scenario_gym/entity/__init__.py
scenario_gym/entity/base.py
scenario_gym/entity/batch.py
scenario_gym/entity/misc.py
scenario_gym/entity/pedestrian.py
scenario_gym/entity/vehicle.py
scenario_gym/integrations/__init__.py
scenario_gym/integrations/argoverse.py
scenario_gym/integrations/deepmind_env.py
scenario_gym/integrations/nuScenes.py
scenario_gym/integrations/openaigym.py
scenario_gym/metrics/__init__.py
scenario_gym/metrics/base.py
scenario_gym/metrics/collision.py
scenario_gym/metrics/trajectory.py
scenario_gym/metrics/rss/__init__.py
scenario_gym/metrics/rss/callback.py
scenario_gym/metrics/rss/rss.py
scenario_gym/metrics/rss/rss_utils.py
scenario_gym/pedestrian/__init__.py
scenario_gym/pedestrian/action.py
scenario_gym/pedestrian/agent.py
scenario_gym/pedestrian/behaviour.py
scenario_gym/pedestrian/config.py
scenario_gym/pedestrian/controller.py
scenario_gym/pedestrian/observation.py
scenario_gym/pedestrian/random_walk.py
scenario_gym/pedestrian/route.py
scenario_gym/pedestrian/sensor.py
scenario_gym/pedestrian/social_force.py
scenario_gym/road_network/__init__.py
scenario_gym/road_network/base.py
scenario_gym/road_network/objects.py
scenario_gym/road_network/road_network.py
scenario_gym/road_network/utils.py
scenario_gym/road_network/xodr.py
scenario_gym/scenario/__init__.py
scenario_gym/scenario/actions.py
scenario_gym/scenario/scenario.py
scenario_gym/sensor/__init__.py
scenario_gym/sensor/base.py
scenario_gym/sensor/common.py
scenario_gym/sensor/map.py
scenario_gym/state/__init__.py
scenario_gym/state/state.py
scenario_gym/state/utils.py
scenario_gym/viewer/__init__.py
scenario_gym/viewer/base.py
scenario_gym/viewer/opencv.py
scenario_gym/viewer/utils.py
scenario_gym-0.4.5.dist-info/LICENSE
scenario_gym-0.4.5.dist-info/METADATA
scenario_gym-0.4.5.dist-info/WHEEL
scenario_gym-0.4.5.dist-info/top_level.txt
scenario_gym-0.4.5.dist-info/RECORD
