Metadata-Version: 2.1
Name: scenario-gym
Version: 0.4.5
Summary: scenario_gym - a lightweight framework for learning from scenario data.
Author-email: Hamish Scott <hamish@drisk.ai>
Project-URL: Homepage, https://github.com/driskai/scenario_gym
Classifier: Programming Language :: Python :: 3
Classifier: License :: OSI Approved :: MIT License
Classifier: Operating System :: OS Independent
Requires-Python: >=3.7
License-File: LICENSE
Requires-Dist: lxml >=4.9.1
Requires-Dist: matplotlib >=3.5.0
Requires-Dist: numpy >=1.21.0
Requires-Dist: opencv-python >=4.5.3.56
Requires-Dist: pyxodr >=0.1.3
Requires-Dist: PyYAML >=6.0
Requires-Dist: setuptools >=61.0.0
Requires-Dist: scenariogeneration >=0.11.0
Requires-Dist: scipy >=1.7.0
Requires-Dist: Shapely >=2.0.0
Provides-Extra: dev
Requires-Dist: gym >=0.21.0 ; extra == 'dev'
Requires-Dist: black ~=22.3.0 ; extra == 'dev'
Requires-Dist: dm-env >=1.5.0 ; extra == 'dev'
Requires-Dist: flake8 ~=3.9.2 ; extra == 'dev'
Requires-Dist: isort >=5.10.1 ; extra == 'dev'
Requires-Dist: pre-commit ~=2.16.0 ; extra == 'dev'
Requires-Dist: pydocstyle ~=6.1.1 ; extra == 'dev'
Requires-Dist: importlib-metadata <5.0.0 ; extra == 'dev'
Requires-Dist: Sphinx ~=4.4.0 ; extra == 'dev'
Requires-Dist: pandas >=1.1.5 ; extra == 'dev'
Requires-Dist: pytest ~=6.2.4 ; extra == 'dev'
Provides-Extra: docs
Requires-Dist: Sphinx ~=4.4.0 ; extra == 'docs'
Provides-Extra: gym
Requires-Dist: gym >=0.21.0 ; extra == 'gym'
Provides-Extra: hooks
Requires-Dist: black ~=22.3.0 ; extra == 'hooks'
Requires-Dist: flake8 ~=3.9.2 ; extra == 'hooks'
Requires-Dist: isort >=5.10.1 ; extra == 'hooks'
Requires-Dist: pre-commit ~=2.16.0 ; extra == 'hooks'
Requires-Dist: pydocstyle ~=6.1.1 ; extra == 'hooks'
Requires-Dist: importlib-metadata <5.0.0 ; extra == 'hooks'
Provides-Extra: integrations
Requires-Dist: pandas >=1.1.5 ; extra == 'integrations'
Provides-Extra: testing
Requires-Dist: pytest ~=6.2.4 ; extra == 'testing'
